{
  "ticker": "DE",
  "timestamp": "20260209_153049",
  "total_strategies": 9848,
  "top_strategies_saved": 13,
  "strategies": [
    {
      "name": "momentum_lb20_z0.5_e20d \u00d7 trailing_stop_5%",
      "entry": "momentum_lb20_z0.5_e20d",
      "exit": "trailing_stop_5%",
      "entry_params": {
        "entry_type": "momentum",
        "lookback_days": 20,
        "zscore_threshold": 0.5,
        "zscore_window": 60,
        "entry_days_before": 20
      },
      "exit_params": {
        "exit_type": "trailing_stop_5%"
      },
      "sharpe": 1.5118966916526317,
      "total_return": 0.37569778907314877,
      "annualized_return": 0.1848558337311037,
      "max_drawdown": -0.17633976847559696,
      "n_trades": 78,
      "win_rate": 0.46153846153846156,
      "signal_accuracy": 0.37037037037037035,
      "direction_accuracy": 0.46153846153846156,
      "skill_ratio": 0.4915254237288136,
      "hhi": 0.024313930484189828,
      "top1_pct": 0.10821958073423944,
      "top3_pct": 0.3117751458344626,
      "return_ex_top1": 0.14142480170499994,
      "return_ex_top3": -0.19805178754943908,
      "profit_factor": 1.309165270570657,
      "expectancy": 0.0057420991517062,
      "tail_ratio": 1.8754894061602045,
      "max_single_contribution": 0.20524609857627496
    },
    {
      "name": "corr_aware_contemp_noshift_e30d \u00d7 trailing_stop_5%",
      "entry": "corr_aware_contemp_noshift_e30d",
      "exit": "trailing_stop_5%",
      "entry_params": {
        "entry_type": "correlation_aware",
        "signal_col": "visible_revenue_resid",
        "corr_col": "contemp",
        "min_signal_abs": 0.0,
        "min_confidence": 0.0,
        "skip_regime_shifts": true,
        "scale_by_confidence": false,
        "confidence_col": "contemp",
        "entry_days_before": 30,
        "use_prior_quarter_corr": true,
        "target_next_quarter": false,
        "date_col": "earnings_date"
      },
      "exit_params": {
        "exit_type": "trailing_stop_5%"
      },
      "sharpe": 1.5089739077617528,
      "total_return": 1.6497956399081115,
      "annualized_return": 0.17511555482816554,
      "max_drawdown": -0.127760815771092,
      "n_trades": 75,
      "win_rate": 0.52,
      "signal_accuracy": 0.34782608695652173,
      "direction_accuracy": 0.52,
      "skill_ratio": 0.5217391304347826,
      "hhi": 0.03436934346969102,
      "top1_pct": 0.15350006218058307,
      "top3_pct": 0.367975299603302,
      "return_ex_top1": 0.9946818803468718,
      "return_ex_top3": 0.32024933038088177,
      "profit_factor": 2.1132773556179547,
      "expectancy": 0.015028655713910165,
      "tail_ratio": 3.1824113332611135,
      "max_single_contribution": 0.32843019531882245
    },
    {
      "name": "corr_aware_contemp_e30d \u00d7 trailing_stop_5%",
      "entry": "corr_aware_contemp_e30d",
      "exit": "trailing_stop_5%",
      "entry_params": {
        "entry_type": "correlation_aware",
        "signal_col": "visible_revenue_resid",
        "corr_col": "contemp",
        "min_signal_abs": 0.0,
        "min_confidence": 0.0,
        "skip_regime_shifts": false,
        "scale_by_confidence": false,
        "confidence_col": "contemp",
        "entry_days_before": 30,
        "use_prior_quarter_corr": true,
        "target_next_quarter": false,
        "date_col": "earnings_date"
      },
      "exit_params": {
        "exit_type": "trailing_stop_5%"
      },
      "sharpe": 1.4485210870376686,
      "total_return": 1.2539863223322008,
      "annualized_return": 0.1806601099606,
      "max_drawdown": -0.1277608157710919,
      "n_trades": 93,
      "win_rate": 0.5053763440860215,
      "signal_accuracy": 0.37037037037037035,
      "direction_accuracy": 0.5053763440860215,
      "skill_ratio": 0.49382716049382713,
      "hhi": 0.02652063445135218,
      "top1_pct": 0.14094424495946972,
      "top3_pct": 0.3378760896220834,
      "return_ex_top1": 0.6967292148845246,
      "return_ex_top3": 0.12303903287045426,
      "profit_factor": 1.7194058062542887,
      "expectancy": 0.010483549068591084,
      "tail_ratio": 2.7739409767997185,
      "max_single_contribution": 0.32843019531882245
    },
    {
      "name": "momentum_lb10_z0.5_e15d \u00d7 trailing_stop_5%",
      "entry": "momentum_lb10_z0.5_e15d",
      "exit": "trailing_stop_5%",
      "entry_params": {
        "entry_type": "momentum",
        "lookback_days": 10,
        "zscore_threshold": 0.5,
        "zscore_window": 60,
        "entry_days_before": 15
      },
      "exit_params": {
        "exit_type": "trailing_stop_5%"
      },
      "sharpe": 1.333488022679,
      "total_return": 0.21004718863356286,
      "annualized_return": 0.13594709324600696,
      "max_drawdown": -0.18039209683828134,
      "n_trades": 64,
      "win_rate": 0.4375,
      "signal_accuracy": 0.3409090909090909,
      "direction_accuracy": 0.4375,
      "skill_ratio": 0.37254901960784315,
      "hhi": 0.028857768772455477,
      "top1_pct": 0.1662915543648545,
      "top3_pct": 0.3530717745872252,
      "return_ex_top1": -0.056164801358635885,
      "return_ex_top3": -0.2962797763825936,
      "profit_factor": 1.2312444451191085,
      "expectancy": 0.004977465981009229,
      "tail_ratio": 1.9089060307883452,
      "max_single_contribution": 0.2820534669351247
    },
    {
      "name": "momentum_lb10_z1.5_e0d \u00d7 trailing_stop_5%",
      "entry": "momentum_lb10_z1.5_e0d",
      "exit": "trailing_stop_5%",
      "entry_params": {
        "entry_type": "momentum",
        "lookback_days": 10,
        "zscore_threshold": 1.5,
        "zscore_window": 60,
        "entry_days_before": 0
      },
      "exit_params": {
        "exit_type": "trailing_stop_5%"
      },
      "sharpe": 1.2739924570755163,
      "total_return": -0.22012344610855517,
      "annualized_return": 0.15627251044601365,
      "max_drawdown": -0.0724712418188412,
      "n_trades": 45,
      "win_rate": 0.28888888888888886,
      "signal_accuracy": 0.3103448275862069,
      "direction_accuracy": 0.29545454545454547,
      "skill_ratio": 0.2571428571428571,
      "hhi": 0.06015785454274208,
      "top1_pct": 0.4352002612534585,
      "top3_pct": 0.6439164194888035,
      "return_ex_top1": -0.4302981493828968,
      "return_ex_top3": -0.519128707079029,
      "profit_factor": 0.8425096419208665,
      "expectancy": -0.0035213585045413068,
      "tail_ratio": 2.580583478702772,
      "max_single_contribution": 0.36892052052609525
    },
    {
      "name": "corr_aware_leading_tgtQ+1_conf0.3_sameq_e5d \u00d7 sl-10%_tp20%",
      "entry": "corr_aware_leading_tgtQ+1_conf0.3_sameq_e5d",
      "exit": "sl-10%_tp20%",
      "entry_params": {
        "entry_type": "correlation_aware",
        "signal_col": "visible_revenue_resid",
        "corr_col": "leading",
        "min_signal_abs": 0.0,
        "min_confidence": 0.3,
        "skip_regime_shifts": false,
        "scale_by_confidence": false,
        "confidence_col": "leading",
        "entry_days_before": 5,
        "use_prior_quarter_corr": false,
        "target_next_quarter": true,
        "date_col": "earnings_date"
      },
      "exit_params": {
        "exit_type": "sl-10%_tp20%"
      },
      "sharpe": 0.566546338751132,
      "total_return": 1.842165737381793,
      "annualized_return": 0.08110947129949198,
      "max_drawdown": -0.25055040905313997,
      "n_trades": 21,
      "win_rate": 0.7142857142857143,
      "signal_accuracy": 0.3,
      "direction_accuracy": 0.7142857142857143,
      "skill_ratio": 0.75,
      "hhi": 0.07410717140205784,
      "top1_pct": 0.13912856359972867,
      "top3_pct": 0.39356018755513916,
      "return_ex_top1": 1.3352978377012157,
      "return_ex_top3": 0.6259016773866752,
      "profit_factor": 4.033737605693045,
      "expectancy": 0.05587110819980007,
      "tail_ratio": 1.9860457088292316,
      "max_single_contribution": 0.21704636192337667
    },
    {
      "name": "corr_aware_leading_tgtQ+1_scaled_sameq_e5d \u00d7 sl-10%_tp20%",
      "entry": "corr_aware_leading_tgtQ+1_scaled_sameq_e5d",
      "exit": "sl-10%_tp20%",
      "entry_params": {
        "entry_type": "correlation_aware",
        "signal_col": "visible_revenue_resid",
        "corr_col": "leading",
        "min_signal_abs": 0.0,
        "min_confidence": 0.0,
        "skip_regime_shifts": false,
        "scale_by_confidence": true,
        "confidence_col": "leading",
        "entry_days_before": 5,
        "use_prior_quarter_corr": false,
        "target_next_quarter": true,
        "date_col": "earnings_date"
      },
      "exit_params": {
        "exit_type": "sl-10%_tp20%"
      },
      "sharpe": 0.5452723161288716,
      "total_return": 1.842165737381793,
      "annualized_return": 0.041997979721500656,
      "max_drawdown": -0.14359077919225915,
      "n_trades": 21,
      "win_rate": 0.7142857142857143,
      "signal_accuracy": 0.3,
      "direction_accuracy": 0.7142857142857143,
      "skill_ratio": 0.75,
      "hhi": 0.07410717140205784,
      "top1_pct": 0.13912856359972867,
      "top3_pct": 0.39356018755513916,
      "return_ex_top1": 1.3352978377012157,
      "return_ex_top3": 0.6259016773866752,
      "profit_factor": 4.033737605693045,
      "expectancy": 0.05587110819980007,
      "tail_ratio": 1.9860457088292316,
      "max_single_contribution": 0.21704636192337667
    },
    {
      "name": "corr_aware_leading_tgtQ+1_conf0.3_scaled_sameq_e5d \u00d7 sl-10%_tp20%",
      "entry": "corr_aware_leading_tgtQ+1_conf0.3_scaled_sameq_e5d",
      "exit": "sl-10%_tp20%",
      "entry_params": {
        "entry_type": "correlation_aware",
        "signal_col": "visible_revenue_resid",
        "corr_col": "leading",
        "min_signal_abs": 0.0,
        "min_confidence": 0.3,
        "skip_regime_shifts": false,
        "scale_by_confidence": true,
        "confidence_col": "leading",
        "entry_days_before": 5,
        "use_prior_quarter_corr": false,
        "target_next_quarter": true,
        "date_col": "earnings_date"
      },
      "exit_params": {
        "exit_type": "sl-10%_tp20%"
      },
      "sharpe": 0.5452723161288716,
      "total_return": 1.842165737381793,
      "annualized_return": 0.041997979721500656,
      "max_drawdown": -0.14359077919225915,
      "n_trades": 21,
      "win_rate": 0.7142857142857143,
      "signal_accuracy": 0.3,
      "direction_accuracy": 0.7142857142857143,
      "skill_ratio": 0.75,
      "hhi": 0.07410717140205784,
      "top1_pct": 0.13912856359972867,
      "top3_pct": 0.39356018755513916,
      "return_ex_top1": 1.3352978377012157,
      "return_ex_top3": 0.6259016773866752,
      "profit_factor": 4.033737605693045,
      "expectancy": 0.05587110819980007,
      "tail_ratio": 1.9860457088292316,
      "max_single_contribution": 0.21704636192337667
    },
    {
      "name": "corr_aware_leading_tgtQ+1_conf0.4_sameq_e5d \u00d7 sl-10%_tp20%",
      "entry": "corr_aware_leading_tgtQ+1_conf0.4_sameq_e5d",
      "exit": "sl-10%_tp20%",
      "entry_params": {
        "entry_type": "correlation_aware",
        "signal_col": "visible_revenue_resid",
        "corr_col": "leading",
        "min_signal_abs": 0.0,
        "min_confidence": 0.4,
        "skip_regime_shifts": false,
        "scale_by_confidence": false,
        "confidence_col": "leading",
        "entry_days_before": 5,
        "use_prior_quarter_corr": false,
        "target_next_quarter": true,
        "date_col": "earnings_date"
      },
      "exit_params": {
        "exit_type": "sl-10%_tp20%"
      },
      "sharpe": 0.5420011190378438,
      "total_return": 1.7892305612063062,
      "annualized_return": 0.07350147519735839,
      "max_drawdown": -0.25055040905313936,
      "n_trades": 18,
      "win_rate": 0.7222222222222222,
      "signal_accuracy": 0.35294117647058826,
      "direction_accuracy": 0.7222222222222222,
      "skill_ratio": 0.7647058823529411,
      "hhi": 0.0880635816895335,
      "top1_pct": 0.15326209392173196,
      "top3_pct": 0.43354043819832705,
      "return_ex_top1": 1.2918030475012525,
      "return_ex_top3": 0.595619350566506,
      "profit_factor": 5.132656190805626,
      "expectancy": 0.06334791905066803,
      "tail_ratio": 2.19150178202186,
      "max_single_contribution": 0.21704636192337667
    },
    {
      "name": "corr_aware_leading_tgtQ+1_conf0.4_scaled_sameq_e5d \u00d7 sl-10%_tp20%",
      "entry": "corr_aware_leading_tgtQ+1_conf0.4_scaled_sameq_e5d",
      "exit": "sl-10%_tp20%",
      "entry_params": {
        "entry_type": "correlation_aware",
        "signal_col": "visible_revenue_resid",
        "corr_col": "leading",
        "min_signal_abs": 0.0,
        "min_confidence": 0.4,
        "skip_regime_shifts": false,
        "scale_by_confidence": true,
        "confidence_col": "leading",
        "entry_days_before": 5,
        "use_prior_quarter_corr": false,
        "target_next_quarter": true,
        "date_col": "earnings_date"
      },
      "exit_params": {
        "exit_type": "sl-10%_tp20%"
      },
      "sharpe": 0.5197666038661906,
      "total_return": 1.7892305612063062,
      "annualized_return": 0.03910582355727521,
      "max_drawdown": -0.14359077919225943,
      "n_trades": 18,
      "win_rate": 0.7222222222222222,
      "signal_accuracy": 0.35294117647058826,
      "direction_accuracy": 0.7222222222222222,
      "skill_ratio": 0.7647058823529411,
      "hhi": 0.0880635816895335,
      "top1_pct": 0.15326209392173196,
      "top3_pct": 0.43354043819832705,
      "return_ex_top1": 1.2918030475012525,
      "return_ex_top3": 0.595619350566506,
      "profit_factor": 5.132656190805626,
      "expectancy": 0.06334791905066803,
      "tail_ratio": 2.19150178202186,
      "max_single_contribution": 0.21704636192337667
    },
    {
      "name": "corr_aware_leading_tgtQ+1_scaled_sameq_e5d \u00d7 sl-10%_tp20%",
      "entry": "corr_aware_leading_tgtQ+1_scaled_sameq_e5d",
      "exit": "sl-10%_tp20%",
      "entry_params": {
        "entry_type": "correlation_aware",
        "signal_col": "visible_revenue_resid",
        "corr_col": "leading",
        "min_signal_abs": 0.0,
        "min_confidence": 0.0,
        "skip_regime_shifts": false,
        "scale_by_confidence": true,
        "confidence_col": "contemp",
        "entry_days_before": 5,
        "use_prior_quarter_corr": false,
        "target_next_quarter": true,
        "date_col": "earnings_date"
      },
      "exit_params": {
        "exit_type": "sl-10%_tp20%"
      },
      "sharpe": 0.30946300090863377,
      "total_return": 1.2602140410863556,
      "annualized_return": 0.025113328805568713,
      "max_drawdown": -0.23036057287580164,
      "n_trades": 18,
      "win_rate": 0.7222222222222222,
      "signal_accuracy": 0.17647058823529413,
      "direction_accuracy": 0.7222222222222222,
      "skill_ratio": 0.7058823529411765,
      "hhi": 0.09932842739108376,
      "top1_pct": 0.18368215277630107,
      "top3_pct": 0.5195912372469412,
      "return_ex_top1": 0.8571306006078474,
      "return_ex_top3": 0.29298786215068917,
      "profit_factor": 4.379009736733922,
      "expectancy": 0.0506554965910626,
      "tail_ratio": 1.6702213672767336,
      "max_single_contribution": 0.21704636192337667
    },
    {
      "name": "corr_aware_leading_tgtQ+1_conf0.3_scaled_sameq_e5d \u00d7 sl-10%_tp20%",
      "entry": "corr_aware_leading_tgtQ+1_conf0.3_scaled_sameq_e5d",
      "exit": "sl-10%_tp20%",
      "entry_params": {
        "entry_type": "correlation_aware",
        "signal_col": "visible_revenue_resid",
        "corr_col": "leading",
        "min_signal_abs": 0.0,
        "min_confidence": 0.3,
        "skip_regime_shifts": false,
        "scale_by_confidence": true,
        "confidence_col": "contemp",
        "entry_days_before": 5,
        "use_prior_quarter_corr": false,
        "target_next_quarter": true,
        "date_col": "earnings_date"
      },
      "exit_params": {
        "exit_type": "sl-10%_tp20%"
      },
      "sharpe": 0.30946300090863377,
      "total_return": 1.2602140410863556,
      "annualized_return": 0.025113328805568713,
      "max_drawdown": -0.23036057287580164,
      "n_trades": 18,
      "win_rate": 0.7222222222222222,
      "signal_accuracy": 0.17647058823529413,
      "direction_accuracy": 0.7222222222222222,
      "skill_ratio": 0.7058823529411765,
      "hhi": 0.09932842739108376,
      "top1_pct": 0.18368215277630107,
      "top3_pct": 0.5195912372469412,
      "return_ex_top1": 0.8571306006078474,
      "return_ex_top3": 0.29298786215068917,
      "profit_factor": 4.379009736733922,
      "expectancy": 0.0506554965910626,
      "tail_ratio": 1.6702213672767336,
      "max_single_contribution": 0.21704636192337667
    },
    {
      "name": "corr_aware_leading_tgtQ+1_conf0.4_scaled_sameq_e5d \u00d7 sl-10%_tp20%",
      "entry": "corr_aware_leading_tgtQ+1_conf0.4_scaled_sameq_e5d",
      "exit": "sl-10%_tp20%",
      "entry_params": {
        "entry_type": "correlation_aware",
        "signal_col": "visible_revenue_resid",
        "corr_col": "leading",
        "min_signal_abs": 0.0,
        "min_confidence": 0.4,
        "skip_regime_shifts": false,
        "scale_by_confidence": true,
        "confidence_col": "contemp",
        "entry_days_before": 5,
        "use_prior_quarter_corr": false,
        "target_next_quarter": true,
        "date_col": "earnings_date"
      },
      "exit_params": {
        "exit_type": "sl-10%_tp20%"
      },
      "sharpe": 0.30722067162084726,
      "total_return": 0.9397559138965992,
      "annualized_return": 0.022645398318586807,
      "max_drawdown": -0.25122995798895215,
      "n_trades": 18,
      "win_rate": 0.6666666666666666,
      "signal_accuracy": 0.17647058823529413,
      "direction_accuracy": 0.6666666666666666,
      "skill_ratio": 0.6470588235294118,
      "hhi": 0.09078633018257806,
      "top1_pct": 0.1914127112163324,
      "top3_pct": 0.5414590690626837,
      "return_ex_top1": 0.5938225318147117,
      "return_ex_top3": 0.10966519392023089,
      "profit_factor": 3.017122667973264,
      "expectancy": 0.042116141194830044,
      "tail_ratio": 1.9966236995135975,
      "max_single_contribution": 0.21704636192337667
    }
  ],
  "buy_hold_total_return": 1.9712032345179797,
  "buy_hold_annualized_return": 0.19958530489299853,
  "buy_hold_sharpe": 0.6194996993656736,
  "buy_hold_start_date": "2019-11-20",
  "buy_hold_end_date": "2025-11-19",
  "buy_hold_scaled_total_return": 0.44358015552012553,
  "buy_hold_scaled_annualized_return": 0.06327100399069274,
  "buy_hold_scaled_sharpe": 0.7027202973873974
}